LICENSE.txt
MANIFEST.in
README.md
setup.py
ABBA_QuPath_RegistrationExporter.egg-info/PKG-INFO
ABBA_QuPath_RegistrationExporter.egg-info/SOURCES.txt
ABBA_QuPath_RegistrationExporter.egg-info/dependency_links.txt
ABBA_QuPath_RegistrationExporter.egg-info/entry_points.txt
ABBA_QuPath_RegistrationExporter.egg-info/requires.txt
ABBA_QuPath_RegistrationExporter.egg-info/top_level.txt
regexport/__init__.py
regexport/app.py
regexport/get_screenshot.py
regexport/main.py
regexport/model.py
regexport/actions/__init__.py
regexport/actions/download_biop_extensions.py
regexport/actions/load_atlas.py
regexport/actions/load_cells.py
regexport/actions/save_cells.py
regexport/actions/save_script.py
regexport/qupath_scripts/__init__.py
regexport/qupath_scripts/export_registered_cells_to_tsv.groovy
regexport/utils/__init__.py
regexport/utils/atlas.py
regexport/utils/exceptions.py
regexport/utils/filters.py
regexport/utils/load_data.py
regexport/utils/parallel.py
regexport/utils/point_cloud.py
regexport/utils/profiling.py
regexport/utils/screenshots.py
regexport/views/__init__.py
regexport/views/channel_filter.py
regexport/views/checkbox.py
regexport/views/histogram.py
regexport/views/histogram2.py
regexport/views/labelled_slider.py
regexport/views/main_window.py
regexport/views/plot_3d.py
regexport/views/region_tree.py
regexport/views/sidebar.py
regexport/views/text_selector.py
regexport/views/utils.py