Metadata-Version: 2.1
Name: ABBA-QuPath-RegistrationExporter
Version: 0.4.2
Summary: A QuPath-Abba Registration Exporter Application for Mouse Sections
Home-page: UNKNOWN
Author: Nicholas A. Del Grosso and Estelle Nassar
Author-email: delgrosso.nick@gmail.com
License: MIT
Platform: UNKNOWN
Provides-Extra: dev
Provides-Extra: ci
License-File: LICENSE.txt
